{
  "Radius": {
    "raw": 3241
  },
  "Points": [
    {
      "x": {
        "raw": 6304
      },
      "y": {
        "raw": -1259757
      }
    },
    {
      "x": {
        "raw": 138937
      },
      "y": {
        "raw": -1252075
      }
    },
    {
      "x": {
        "raw": -210319
      },
      "y": {
        "raw": -1242092
      }
    },
    {
      "x": {
        "raw": 280160
      },
      "y": {
        "raw": -1228226
      }
    },
    {
      "x": {
        "raw": -338238
      },
      "y": {
        "raw": -1213517
      }
    },
    {
      "x": {
        "raw": 406260
      },
      "y": {
        "raw": -1192468
      }
    },
    {
      "x": {
        "raw": -96051
      },
      "y": {
        "raw": -1177883
      }
    },
    {
      "x": {
        "raw": 60494
      },
      "y": {
        "raw": -1140412
      }
    },
    {
      "x": {
        "raw": -537028
      },
      "y": {
        "raw": -1139574
      }
    },
    {
      "x": {
        "raw": 191288
      },
      "y": {
        "raw": -1131884
      }
    },
    {
      "x": {
        "raw": 605177
      },
      "y": {
        "raw": -1104893
      }
    },
    {
      "x": {
        "raw": -410778
      },
      "y": {
        "raw": -1104348
      }
    },
    {
      "x": {
        "raw": 317389
      },
      "y": {
        "raw": -1096126
      }
    },
    {
      "x": {
        "raw": -279965
      },
      "y": {
        "raw": -1096111
      }
    },
    {
      "x": {
        "raw": 476190
      },
      "y": {
        "raw": -1081609
      }
    },
    {
      "x": {
        "raw": -652527
      },
      "y": {
        "raw": -1077607
      }
    },
    {
      "x": {
        "raw": -153891
      },
      "y": {
        "raw": -1060263
      }
    },
    {
      "x": {
        "raw": -24320
      },
      "y": {
        "raw": -1040480
      }
    },
    {
      "x": {
        "raw": 716704
      },
      "y": {
        "raw": -1036033
      }
    },
    {
      "x": {
        "raw": 104591
      },
      "y": {
        "raw": -1016776
      }
    },
    {
      "x": {
        "raw": -506931
      },
      "y": {
        "raw": -1011544
      }
    },
    {
      "x": {
        "raw": 233861
      },
      "y": {
        "raw": -995116
      }
    },
    {
      "x": {
        "raw": -366623
      },
      "y": {
        "raw": -980937
      }
    },
    {
      "x": {
        "raw": 363102
      },
      "y": {
        "raw": -973284
      }
    },
    {
      "x": {
        "raw": -237364
      },
      "y": {
        "raw": -959209
      }
    },
    {
      "x": {
        "raw": -699022
      },
      "y": {
        "raw": -955058
      }
    },
    {
      "x": {
        "raw": 492357
      },
      "y": {
        "raw": -951538
      }
    },
    {
      "x": {
        "raw": -829892
      },
      "y": {
        "raw": -947790
      }
    },
    {
      "x": {
        "raw": 623221
      },
      "y": {
        "raw": -944158
      }
    },
    {
      "x": {
        "raw": -108112
      },
      "y": {
        "raw": -937445
      }
    },
    {
      "x": {
        "raw": 21144
      },
      "y": {
        "raw": -915699
      }
    },
    {
      "x": {
        "raw": 749528
      },
      "y": {
        "raw": -909137
      }
    },
    {
      "x": {
        "raw": -579339
      },
      "y": {
        "raw": -901618
      }
    },
    {
      "x": {
        "raw": 880355
      },
      "y": {
        "raw": -901112
      }
    },
    {
      "x": {
        "raw": 150402
      },
      "y": {
        "raw": -893970
      }
    },
    {
      "x": {
        "raw": -450083
      },
      "y": {
        "raw": -879872
      }
    },
    {
      "x": {
        "raw": 279655
      },
      "y": {
        "raw": -872207
      }
    },
    {
      "x": {
        "raw": -320828
      },
      "y": {
        "raw": -858126
      }
    },
    {
      "x": {
        "raw": -923879
      },
      "y": {
        "raw": -856432
      }
    },
    {
      "x": {
        "raw": 408910
      },
      "y": {
        "raw": -850461
      }
    },
    {
      "x": {
        "raw": -191572
      },
      "y": {
        "raw": -836380
      }
    },
    {
      "x": {
        "raw": 538169
      },
      "y": {
        "raw": -828732
      }
    },
    {
      "x": {
        "raw": -792055
      },
      "y": {
        "raw": -822298
      }
    },
    {
      "x": {
        "raw": -62317
      },
      "y": {
        "raw": -814634
      }
    },
    {
      "x": {
        "raw": 667421
      },
      "y": {
        "raw": -806969
      }
    },
    {
      "x": {
        "raw": 969218
      },
      "y": {
        "raw": -804763
      }
    },
    {
      "x": {
        "raw": -662799
      },
      "y": {
        "raw": -800552
      }
    },
    {
      "x": {
        "raw": 66939
      },
      "y": {
        "raw": -792888
      }
    },
    {
      "x": {
        "raw": 799017
      },
      "y": {
        "raw": -786916
      }
    },
    {
      "x": {
        "raw": -533544
      },
      "y": {
        "raw": -778806
      }
    },
    {
      "x": {
        "raw": 196194
      },
      "y": {
        "raw": -771142
      }
    },
    {
      "x": {
        "raw": -404288
      },
      "y": {
        "raw": -757060
      }
    },
    {
      "x": {
        "raw": 325450
      },
      "y": {
        "raw": -749396
      }
    },
    {
      "x": {
        "raw": -1016461
      },
      "y": {
        "raw": -744197
      }
    },
    {
      "x": {
        "raw": -275033
      },
      "y": {
        "raw": -735314
      }
    },
    {
      "x": {
        "raw": -886041
      },
      "y": {
        "raw": -730940
      }
    },
    {
      "x": {
        "raw": 454705
      },
      "y": {
        "raw": -727650
      }
    },
    {
      "x": {
        "raw": -145777
      },
      "y": {
        "raw": -713568
      }
    },
    {
      "x": {
        "raw": 583961
      },
      "y": {
        "raw": -705904
      }
    },
    {
      "x": {
        "raw": -746260
      },
      "y": {
        "raw": -699487
      }
    },
    {
      "x": {
        "raw": -16522
      },
      "y": {
        "raw": -691822
      }
    },
    {
      "x": {
        "raw": 713217
      },
      "y": {
        "raw": -684158
      }
    },
    {
      "x": {
        "raw": -617004
      },
      "y": {
        "raw": -677741
      }
    },
    {
      "x": {
        "raw": 973053
      },
      "y": {
        "raw": -673747
      }
    },
    {
      "x": {
        "raw": 112734
      },
      "y": {
        "raw": -670076
      }
    },
    {
      "x": {
        "raw": 842472
      },
      "y": {
        "raw": -662411
      }
    },
    {
      "x": {
        "raw": -487749
      },
      "y": {
        "raw": -655995
      }
    },
    {
      "x": {
        "raw": 241990
      },
      "y": {
        "raw": -648330
      }
    },
    {
      "x": {
        "raw": -358493
      },
      "y": {
        "raw": -634249
      }
    },
    {
      "x": {
        "raw": -1089294
      },
      "y": {
        "raw": -632824
      }
    },
    {
      "x": {
        "raw": 371245
      },
      "y": {
        "raw": -626584
      }
    },
    {
      "x": {
        "raw": 1094341
      },
      "y": {
        "raw": -624056
      }
    },
    {
      "x": {
        "raw": -958683
      },
      "y": {
        "raw": -621839
      }
    },
    {
      "x": {
        "raw": -229237
      },
      "y": {
        "raw": -612503
      }
    },
    {
      "x": {
        "raw": 500501
      },
      "y": {
        "raw": -604838
      }
    },
    {
      "x": {
        "raw": -829720
      },
      "y": {
        "raw": -598421
      }
    },
    {
      "x": {
        "raw": -99982
      },
      "y": {
        "raw": -590757
      }
    },
    {
      "x": {
        "raw": 629756
      },
      "y": {
        "raw": -583092
      }
    },
    {
      "x": {
        "raw": -700465
      },
      "y": {
        "raw": -576675
      }
    },
    {
      "x": {
        "raw": 29274
      },
      "y": {
        "raw": -569011
      }
    },
    {
      "x": {
        "raw": 759012
      },
      "y": {
        "raw": -561346
      }
    },
    {
      "x": {
        "raw": -571209
      },
      "y": {
        "raw": -554929
      }
    },
    {
      "x": {
        "raw": 158529
      },
      "y": {
        "raw": -547264
      }
    },
    {
      "x": {
        "raw": 888267
      },
      "y": {
        "raw": -539600
      }
    },
    {
      "x": {
        "raw": -441953
      },
      "y": {
        "raw": -533183
      }
    },
    {
      "x": {
        "raw": 287785
      },
      "y": {
        "raw": -525518
      }
    },
    {
      "x": {
        "raw": 1017523
      },
      "y": {
        "raw": -517854
      }
    },
    {
      "x": {
        "raw": -312698
      },
      "y": {
        "raw": -511437
      }
    },
    {
      "x": {
        "raw": 1153259
      },
      "y": {
        "raw": -506973
      }
    },
    {
      "x": {
        "raw": 417040
      },
      "y": {
        "raw": -503772
      }
    },
    {
      "x": {
        "raw": -1070690
      },
      "y": {
        "raw": -503078
      }
    },
    {
      "x": {
        "raw": -913648
      },
      "y": {
        "raw": -497206
      }
    },
    {
      "x": {
        "raw": -183442
      },
      "y": {
        "raw": -489691
      }
    },
    {
      "x": {
        "raw": 546296
      },
      "y": {
        "raw": -482026
      }
    },
    {
      "x": {
        "raw": -783925
      },
      "y": {
        "raw": -475610
      }
    },
    {
      "x": {
        "raw": -54187
      },
      "y": {
        "raw": -467945
      }
    },
    {
      "x": {
        "raw": 675551
      },
      "y": {
        "raw": -460280
      }
    },
    {
      "x": {
        "raw": -654669
      },
      "y": {
        "raw": -453864
      }
    },
    {
      "x": {
        "raw": 75069
      },
      "y": {
        "raw": -446199
      }
    },
    {
      "x": {
        "raw": 804807
      },
      "y": {
        "raw": -438534
      }
    },
    {
      "x": {
        "raw": -1182441
      },
      "y": {
        "raw": -434582
      }
    },
    {
      "x": {
        "raw": -525414
      },
      "y": {
        "raw": -432118
      }
    },
    {
      "x": {
        "raw": 204324
      },
      "y": {
        "raw": -424453
      }
    },
    {
      "x": {
        "raw": 934062
      },
      "y": {
        "raw": -416788
      }
    },
    {
      "x": {
        "raw": -396158
      },
      "y": {
        "raw": -410371
      }
    },
    {
      "x": {
        "raw": 333580
      },
      "y": {
        "raw": -402707
      }
    },
    {
      "x": {
        "raw": 1076441
      },
      "y": {
        "raw": -400770
      }
    },
    {
      "x": {
        "raw": -996889
      },
      "y": {
        "raw": -394758
      }
    },
    {
      "x": {
        "raw": -266903
      },
      "y": {
        "raw": -388625
      }
    },
    {
      "x": {
        "raw": 462835
      },
      "y": {
        "raw": -380961
      }
    },
    {
      "x": {
        "raw": -867385
      },
      "y": {
        "raw": -374544
      }
    },
    {
      "x": {
        "raw": 1204366
      },
      "y": {
        "raw": -369208
      }
    },
    {
      "x": {
        "raw": -137647
      },
      "y": {
        "raw": -366879
      }
    },
    {
      "x": {
        "raw": 592091
      },
      "y": {
        "raw": -359215
      }
    },
    {
      "x": {
        "raw": -738130
      },
      "y": {
        "raw": -352798
      }
    },
    {
      "x": {
        "raw": -8392
      },
      "y": {
        "raw": -345133
      }
    },
    {
      "x": {
        "raw": 721346
      },
      "y": {
        "raw": -337469
      }
    },
    {
      "x": {
        "raw": -608874
      },
      "y": {
        "raw": -331052
      }
    },
    {
      "x": {
        "raw": 120864
      },
      "y": {
        "raw": -323387
      }
    },
    {
      "x": {
        "raw": 850602
      },
      "y": {
        "raw": -315723
      }
    },
    {
      "x": {
        "raw": -1221195
      },
      "y": {
        "raw": -309370
      }
    },
    {
      "x": {
        "raw": -479619
      },
      "y": {
        "raw": -309306
      }
    },
    {
      "x": {
        "raw": 250119
      },
      "y": {
        "raw": -301641
      }
    },
    {
      "x": {
        "raw": -1087513
      },
      "y": {
        "raw": -298939
      }
    },
    {
      "x": {
        "raw": 979858
      },
      "y": {
        "raw": -293977
      }
    },
    {
      "x": {
        "raw": -350363
      },
      "y": {
        "raw": -287560
      }
    },
    {
      "x": {
        "raw": 379375
      },
      "y": {
        "raw": -279895
      }
    },
    {
      "x": {
        "raw": 1109384
      },
      "y": {
        "raw": -273906
      }
    },
    {
      "x": {
        "raw": -951094
      },
      "y": {
        "raw": -271947
      }
    },
    {
      "x": {
        "raw": -221108
      },
      "y": {
        "raw": -265814
      }
    },
    {
      "x": {
        "raw": 508631
      },
      "y": {
        "raw": -258149
      }
    },
    {
      "x": {
        "raw": -821590
      },
      "y": {
        "raw": -251732
      }
    },
    {
      "x": {
        "raw": -91852
      },
      "y": {
        "raw": -244068
      }
    },
    {
      "x": {
        "raw": 1236399
      },
      "y": {
        "raw": -241548
      }
    },
    {
      "x": {
        "raw": 637886
      },
      "y": {
        "raw": -236403
      }
    },
    {
      "x": {
        "raw": -692335
      },
      "y": {
        "raw": -229986
      }
    },
    {
      "x": {
        "raw": 37404
      },
      "y": {
        "raw": -222322
      }
    },
    {
      "x": {
        "raw": 767142
      },
      "y": {
        "raw": -214657
      }
    },
    {
      "x": {
        "raw": -563079
      },
      "y": {
        "raw": -208240
      }
    },
    {
      "x": {
        "raw": 166659
      },
      "y": {
        "raw": -200576
      }
    },
    {
      "x": {
        "raw": 896397
      },
      "y": {
        "raw": -192911
      }
    },
    {
      "x": {
        "raw": -1164005
      },
      "y": {
        "raw": -191433
      }
    },
    {
      "x": {
        "raw": -433823
      },
      "y": {
        "raw": -186494
      }
    },
    {
      "x": {
        "raw": 295915
      },
      "y": {
        "raw": -178830
      }
    },
    {
      "x": {
        "raw": 1026798
      },
      "y": {
        "raw": -171057
      }
    },
    {
      "x": {
        "raw": -1034554
      },
      "y": {
        "raw": -170881
      }
    },
    {
      "x": {
        "raw": -304568
      },
      "y": {
        "raw": -164748
      }
    },
    {
      "x": {
        "raw": 425170
      },
      "y": {
        "raw": -157084
      }
    },
    {
      "x": {
        "raw": -905299
      },
      "y": {
        "raw": -149135
      }
    },
    {
      "x": {
        "raw": -175312
      },
      "y": {
        "raw": -143002
      }
    },
    {
      "x": {
        "raw": 554426
      },
      "y": {
        "raw": -135338
      }
    },
    {
      "x": {
        "raw": -775795
      },
      "y": {
        "raw": -128921
      }
    },
    {
      "x": {
        "raw": 1176364
      },
      "y": {
        "raw": -125033
      }
    },
    {
      "x": {
        "raw": -46057
      },
      "y": {
        "raw": -121256
      }
    },
    {
      "x": {
        "raw": 683681
      },
      "y": {
        "raw": -113592
      }
    },
    {
      "x": {
        "raw": -646539
      },
      "y": {
        "raw": -107175
      }
    },
    {
      "x": {
        "raw": 83199
      },
      "y": {
        "raw": -99510
      }
    },
    {
      "x": {
        "raw": -1255953
      },
      "y": {
        "raw": -98023
      }
    },
    {
      "x": {
        "raw": 812937
      },
      "y": {
        "raw": -91846
      }
    },
    {
      "x": {
        "raw": -517284
      },
      "y": {
        "raw": -85429
      }
    },
    {
      "x": {
        "raw": 212454
      },
      "y": {
        "raw": -77764
      }
    },
    {
      "x": {
        "raw": 942192
      },
      "y": {
        "raw": -70100
      }
    },
    {
      "x": {
        "raw": -1129084
      },
      "y": {
        "raw": -65099
      }
    },
    {
      "x": {
        "raw": -388028
      },
      "y": {
        "raw": -63683
      }
    },
    {
      "x": {
        "raw": 341710
      },
      "y": {
        "raw": -56018
      }
    },
    {
      "x": {
        "raw": -988759
      },
      "y": {
        "raw": -48070
      }
    },
    {
      "x": {
        "raw": 1071181
      },
      "y": {
        "raw": -46825
      }
    },
    {
      "x": {
        "raw": -258773
      },
      "y": {
        "raw": -41937
      }
    },
    {
      "x": {
        "raw": 470965
      },
      "y": {
        "raw": -34272
      }
    },
    {
      "x": {
        "raw": -859504
      },
      "y": {
        "raw": -26323
      }
    },
    {
      "x": {
        "raw": 1259549
      },
      "y": {
        "raw": -23740
      }
    },
    {
      "x": {
        "raw": -129517
      },
      "y": {
        "raw": -20191
      }
    },
    {
      "x": {
        "raw": 600221
      },
      "y": {
        "raw": -12526
      }
    },
    {
      "x": {
        "raw": -730000
      },
      "y": {
        "raw": -6109
      }
    },
    {
      "x": {
        "raw": -262
      },
      "y": {
        "raw": 1555
      }
    },
    {
      "x": {
        "raw": 729476
      },
      "y": {
        "raw": 9220
      }
    },
    {
      "x": {
        "raw": -600744
      },
      "y": {
        "raw": 15637
      }
    },
    {
      "x": {
        "raw": 128994
      },
      "y": {
        "raw": 23301
      }
    },
    {
      "x": {
        "raw": 858732
      },
      "y": {
        "raw": 30966
      }
    },
    {
      "x": {
        "raw": -1259340
      },
      "y": {
        "raw": 33005
      }
    },
    {
      "x": {
        "raw": -471489
      },
      "y": {
        "raw": 37383
      }
    },
    {
      "x": {
        "raw": 258249
      },
      "y": {
        "raw": 45047
      }
    },
    {
      "x": {
        "raw": -1072220
      },
      "y": {
        "raw": 52996
      }
    },
    {
      "x": {
        "raw": 987721
      },
      "y": {
        "raw": 54241
      }
    },
    {
      "x": {
        "raw": -342233
      },
      "y": {
        "raw": 59129
      }
    },
    {
      "x": {
        "raw": 387505
      },
      "y": {
        "raw": 66794
      }
    },
    {
      "x": {
        "raw": 1127516
      },
      "y": {
        "raw": 72417
      }
    },
    {
      "x": {
        "raw": -942964
      },
      "y": {
        "raw": 74742
      }
    },
    {
      "x": {
        "raw": -212978
      },
      "y": {
        "raw": 80875
      }
    },
    {
      "x": {
        "raw": 516760
      },
      "y": {
        "raw": 88540
      }
    },
    {
      "x": {
        "raw": -813709
      },
      "y": {
        "raw": 96488
      }
    },
    {
      "x": {
        "raw": -83722
      },
      "y": {
        "raw": 102621
      }
    },
    {
      "x": {
        "raw": 1255198
      },
      "y": {
        "raw": 107260
      }
    },
    {
      "x": {
        "raw": 646016
      },
      "y": {
        "raw": 110286
      }
    },
    {
      "x": {
        "raw": -684205
      },
      "y": {
        "raw": 116702
      }
    },
    {
      "x": {
        "raw": 45533
      },
      "y": {
        "raw": 124367
      }
    },
    {
      "x": {
        "raw": 775272
      },
      "y": {
        "raw": 132032
      }
    },
    {
      "x": {
        "raw": -1175473
      },
      "y": {
        "raw": 133734
      }
    },
    {
      "x": {
        "raw": -554949
      },
      "y": {
        "raw": 138448
      }
    },
    {
      "x": {
        "raw": 174789
      },
      "y": {
        "raw": 146113
      }
    },
    {
      "x": {
        "raw": 904261
      },
      "y": {
        "raw": 155306
      }
    },
    {
      "x": {
        "raw": -425694
      },
      "y": {
        "raw": 160194
      }
    },
    {
      "x": {
        "raw": 304045
      },
      "y": {
        "raw": 167859
      }
    },
    {
      "x": {
        "raw": 1033516
      },
      "y": {
        "raw": 177052
      }
    },
    {
      "x": {
        "raw": -1032904
      },
      "y": {
        "raw": 178158
      }
    },
    {
      "x": {
        "raw": -296438
      },
      "y": {
        "raw": 181941
      }
    },
    {
      "x": {
        "raw": 433300
      },
      "y": {
        "raw": 189605
      }
    },
    {
      "x": {
        "raw": -897169
      },
      "y": {
        "raw": 197554
      }
    },
    {
      "x": {
        "raw": 1162565
      },
      "y": {
        "raw": 199991
      }
    },
    {
      "x": {
        "raw": -167182
      },
      "y": {
        "raw": 203687
      }
    },
    {
      "x": {
        "raw": 562556
      },
      "y": {
        "raw": 211351
      }
    },
    {
      "x": {
        "raw": -767913
      },
      "y": {
        "raw": 219300
      }
    },
    {
      "x": {
        "raw": -37927
      },
      "y": {
        "raw": 225433
      }
    },
    {
      "x": {
        "raw": 691811
      },
      "y": {
        "raw": 233097
      }
    },
    {
      "x": {
        "raw": -638409
      },
      "y": {
        "raw": 239514
      }
    },
    {
      "x": {
        "raw": 91329
      },
      "y": {
        "raw": 247179
      }
    },
    {
      "x": {
        "raw": -1234570
      },
      "y": {
        "raw": 250727
      }
    },
    {
      "x": {
        "raw": 820800
      },
      "y": {
        "raw": 256372
      }
    },
    {
      "x": {
        "raw": -509154
      },
      "y": {
        "raw": 261260
      }
    },
    {
      "x": {
        "raw": 220584
      },
      "y": {
        "raw": 268925
      }
    },
    {
      "x": {
        "raw": 950056
      },
      "y": {
        "raw": 278118
      }
    },
    {
      "x": {
        "raw": -379898
      },
      "y": {
        "raw": 283006
      }
    },
    {
      "x": {
        "raw": 349840
      },
      "y": {
        "raw": 290671
      }
    },
    {
      "x": {
        "raw": -1111681
      },
      "y": {
        "raw": 296314
      }
    },
    {
      "x": {
        "raw": -980629
      },
      "y": {
        "raw": 298619
      }
    },
    {
      "x": {
        "raw": -250643
      },
      "y": {
        "raw": 304752
      }
    },
    {
      "x": {
        "raw": 1088228
      },
      "y": {
        "raw": 307943
      }
    },
    {
      "x": {
        "raw": 479095
      },
      "y": {
        "raw": 312417
      }
    },
    {
      "x": {
        "raw": 1218886
      },
      "y": {
        "raw": 318345
      }
    },
    {
      "x": {
        "raw": -851374
      },
      "y": {
        "raw": 320365
      }
    },
    {
      "x": {
        "raw": -121387
      },
      "y": {
        "raw": 326498
      }
    },
    {
      "x": {
        "raw": 608351
      },
      "y": {
        "raw": 334163
      }
    },
    {
      "x": {
        "raw": -722118
      },
      "y": {
        "raw": 342111
      }
    },
    {
      "x": {
        "raw": 7868
      },
      "y": {
        "raw": 348244
      }
    },
    {
      "x": {
        "raw": 737340
      },
      "y": {
        "raw": 357437
      }
    },
    {
      "x": {
        "raw": -592614
      },
      "y": {
        "raw": 362326
      }
    },
    {
      "x": {
        "raw": 137124
      },
      "y": {
        "raw": 369990
      }
    },
    {
      "x": {
        "raw": 866595
      },
      "y": {
        "raw": 379183
      }
    },
    {
      "x": {
        "raw": -463359
      },
      "y": {
        "raw": 384072
      }
    },
    {
      "x": {
        "raw": 266379
      },
      "y": {
        "raw": 391736
      }
    },
    {
      "x": {
        "raw": -1195577
      },
      "y": {
        "raw": 397019
      }
    },
    {
      "x": {
        "raw": 995851
      },
      "y": {
        "raw": 400930
      }
    },
    {
      "x": {
        "raw": -334103
      },
      "y": {
        "raw": 405818
      }
    },
    {
      "x": {
        "raw": 395635
      },
      "y": {
        "raw": 413482
      }
    },
    {
      "x": {
        "raw": -1066416
      },
      "y": {
        "raw": 419322
      }
    },
    {
      "x": {
        "raw": -935479
      },
      "y": {
        "raw": 425523
      }
    },
    {
      "x": {
        "raw": -204848
      },
      "y": {
        "raw": 427564
      }
    },
    {
      "x": {
        "raw": 524890
      },
      "y": {
        "raw": 435228
      }
    },
    {
      "x": {
        "raw": -805579
      },
      "y": {
        "raw": 443177
      }
    },
    {
      "x": {
        "raw": 1179212
      },
      "y": {
        "raw": 443269
      }
    },
    {
      "x": {
        "raw": -75592
      },
      "y": {
        "raw": 449310
      }
    },
    {
      "x": {
        "raw": 653879
      },
      "y": {
        "raw": 458503
      }
    },
    {
      "x": {
        "raw": -676323
      },
      "y": {
        "raw": 464923
      }
    },
    {
      "x": {
        "raw": 53663
      },
      "y": {
        "raw": 471056
      }
    },
    {
      "x": {
        "raw": 783135
      },
      "y": {
        "raw": 480249
      }
    },
    {
      "x": {
        "raw": -546819
      },
      "y": {
        "raw": 485137
      }
    },
    {
      "x": {
        "raw": 182919
      },
      "y": {
        "raw": 492802
      }
    },
    {
      "x": {
        "raw": -417564
      },
      "y": {
        "raw": 506883
      }
    },
    {
      "x": {
        "raw": 1067002
      },
      "y": {
        "raw": 511009
      }
    },
    {
      "x": {
        "raw": 924719
      },
      "y": {
        "raw": 512332
      }
    },
    {
      "x": {
        "raw": 312174
      },
      "y": {
        "raw": 514548
      }
    },
    {
      "x": {
        "raw": -1145725
      },
      "y": {
        "raw": 523723
      }
    },
    {
      "x": {
        "raw": -288308
      },
      "y": {
        "raw": 528629
      }
    },
    {
      "x": {
        "raw": 441430
      },
      "y": {
        "raw": 536294
      }
    },
    {
      "x": {
        "raw": -1010082
      },
      "y": {
        "raw": 537671
      }
    },
    {
      "x": {
        "raw": -159053
      },
      "y": {
        "raw": 550375
      }
    },
    {
      "x": {
        "raw": -879717
      },
      "y": {
        "raw": 551266
      }
    },
    {
      "x": {
        "raw": 570419
      },
      "y": {
        "raw": 559569
      }
    },
    {
      "x": {
        "raw": -29797
      },
      "y": {
        "raw": 572121
      }
    },
    {
      "x": {
        "raw": 699675
      },
      "y": {
        "raw": 581315
      }
    },
    {
      "x": {
        "raw": -630528
      },
      "y": {
        "raw": 587735
      }
    },
    {
      "x": {
        "raw": 99459
      },
      "y": {
        "raw": 593867
      }
    },
    {
      "x": {
        "raw": 828930
      },
      "y": {
        "raw": 603061
      }
    },
    {
      "x": {
        "raw": -760391
      },
      "y": {
        "raw": 605498
      }
    },
    {
      "x": {
        "raw": -501024
      },
      "y": {
        "raw": 607949
      }
    },
    {
      "x": {
        "raw": 228714
      },
      "y": {
        "raw": 615613
      }
    },
    {
      "x": {
        "raw": -371768
      },
      "y": {
        "raw": 629695
      }
    },
    {
      "x": {
        "raw": 357970
      },
      "y": {
        "raw": 637359
      }
    },
    {
      "x": {
        "raw": 1084562
      },
      "y": {
        "raw": 640899
      }
    },
    {
      "x": {
        "raw": 953522
      },
      "y": {
        "raw": 643765
      }
    },
    {
      "x": {
        "raw": -1080020
      },
      "y": {
        "raw": 648525
      }
    },
    {
      "x": {
        "raw": -242513
      },
      "y": {
        "raw": 651441
      }
    },
    {
      "x": {
        "raw": 486959
      },
      "y": {
        "raw": 660634
      }
    },
    {
      "x": {
        "raw": -949655
      },
      "y": {
        "raw": 662120
      }
    },
    {
      "x": {
        "raw": -113257
      },
      "y": {
        "raw": 673187
      }
    },
    {
      "x": {
        "raw": 616214
      },
      "y": {
        "raw": 682380
      }
    },
    {
      "x": {
        "raw": 15998
      },
      "y": {
        "raw": 694933
      }
    },
    {
      "x": {
        "raw": 744695
      },
      "y": {
        "raw": 708401
      }
    },
    {
      "x": {
        "raw": -584733
      },
      "y": {
        "raw": 710546
      }
    },
    {
      "x": {
        "raw": 145254
      },
      "y": {
        "raw": 716679
      }
    },
    {
      "x": {
        "raw": -714596
      },
      "y": {
        "raw": 728310
      }
    },
    {
      "x": {
        "raw": -455229
      },
      "y": {
        "raw": 730760
      }
    },
    {
      "x": {
        "raw": 274509
      },
      "y": {
        "raw": 738425
      }
    },
    {
      "x": {
        "raw": -845043
      },
      "y": {
        "raw": 741090
      }
    },
    {
      "x": {
        "raw": 870498
      },
      "y": {
        "raw": 745190
      }
    },
    {
      "x": {
        "raw": -325973
      },
      "y": {
        "raw": 752506
      }
    },
    {
      "x": {
        "raw": 403498
      },
      "y": {
        "raw": 761700
      }
    },
    {
      "x": {
        "raw": 999846
      },
      "y": {
        "raw": 766378
      }
    },
    {
      "x": {
        "raw": -196718
      },
      "y": {
        "raw": 774252
      }
    },
    {
      "x": {
        "raw": -981935
      },
      "y": {
        "raw": 789193
      }
    },
    {
      "x": {
        "raw": -67462
      },
      "y": {
        "raw": 795998
      }
    },
    {
      "x": {
        "raw": 650902
      },
      "y": {
        "raw": 808779
      }
    },
    {
      "x": {
        "raw": 61793
      },
      "y": {
        "raw": 817745
      }
    },
    {
      "x": {
        "raw": 520399
      },
      "y": {
        "raw": 820979
      }
    },
    {
      "x": {
        "raw": -538938
      },
      "y": {
        "raw": 833358
      }
    },
    {
      "x": {
        "raw": 778539
      },
      "y": {
        "raw": 838590
      }
    },
    {
      "x": {
        "raw": 191049
      },
      "y": {
        "raw": 839491
      }
    },
    {
      "x": {
        "raw": -768751
      },
      "y": {
        "raw": 847671
      }
    },
    {
      "x": {
        "raw": -409434
      },
      "y": {
        "raw": 853572
      }
    },
    {
      "x": {
        "raw": 320038
      },
      "y": {
        "raw": 862765
      }
    },
    {
      "x": {
        "raw": 907016
      },
      "y": {
        "raw": 872849
      }
    },
    {
      "x": {
        "raw": -280178
      },
      "y": {
        "raw": 875318
      }
    },
    {
      "x": {
        "raw": -894611
      },
      "y": {
        "raw": 886949
      }
    },
    {
      "x": {
        "raw": -150923
      },
      "y": {
        "raw": 897064
      }
    },
    {
      "x": {
        "raw": -21667
      },
      "y": {
        "raw": 918810
      }
    },
    {
      "x": {
        "raw": 436939
      },
      "y": {
        "raw": 922044
      }
    },
    {
      "x": {
        "raw": -663061
      },
      "y": {
        "raw": 925192
      }
    },
    {
      "x": {
        "raw": 680716
      },
      "y": {
        "raw": 936415
      }
    },
    {
      "x": {
        "raw": 107588
      },
      "y": {
        "raw": 940556
      }
    },
    {
      "x": {
        "raw": 236578
      },
      "y": {
        "raw": 963831
      }
    },
    {
      "x": {
        "raw": -537999
      },
      "y": {
        "raw": 964426
      }
    },
    {
      "x": {
        "raw": 808353
      },
      "y": {
        "raw": 966226
      }
    },
    {
      "x": {
        "raw": -796915
      },
      "y": {
        "raw": 975681
      }
    },
    {
      "x": {
        "raw": -363639
      },
      "y": {
        "raw": 976384
      }
    },
    {
      "x": {
        "raw": 556023
      },
      "y": {
        "raw": 976807
      }
    },
    {
      "x": {
        "raw": -234383
      },
      "y": {
        "raw": 998130
      }
    },
    {
      "x": {
        "raw": -105127
      },
      "y": {
        "raw": 1019876
      }
    },
    {
      "x": {
        "raw": 24128
      },
      "y": {
        "raw": 1041622
      }
    },
    {
      "x": {
        "raw": 449056
      },
      "y": {
        "raw": 1052555
      }
    },
    {
      "x": {
        "raw": -691225
      },
      "y": {
        "raw": 1053202
      }
    },
    {
      "x": {
        "raw": 669285
      },
      "y": {
        "raw": 1066996
      }
    },
    {
      "x": {
        "raw": -457502
      },
      "y": {
        "raw": 1067868
      }
    },
    {
      "x": {
        "raw": 192802
      },
      "y": {
        "raw": 1087377
      }
    },
    {
      "x": {
        "raw": 323818
      },
      "y": {
        "raw": 1091225
      }
    },
    {
      "x": {
        "raw": -317096
      },
      "y": {
        "raw": 1099807
      }
    },
    {
      "x": {
        "raw": -578053
      },
      "y": {
        "raw": 1119322
      }
    },
    {
      "x": {
        "raw": 554843
      },
      "y": {
        "raw": 1130914
      }
    },
    {
      "x": {
        "raw": -191123
      },
      "y": {
        "raw": 1136008
      }
    },
    {
      "x": {
        "raw": -60238
      },
      "y": {
        "raw": 1143021
      }
    },
    {
      "x": {
        "raw": 82889
      },
      "y": {
        "raw": 1158784
      }
    },
    {
      "x": {
        "raw": 433782
      },
      "y": {
        "raw": 1182734
      }
    },
    {
      "x": {
        "raw": -411594
      },
      "y": {
        "raw": 1190638
      }
    },
    {
      "x": {
        "raw": 308544
      },
      "y": {
        "raw": 1221404
      }
    },
    {
      "x": {
        "raw": -285461
      },
      "y": {
        "raw": 1227004
      }
    },
    {
      "x": {
        "raw": 179966
      },
      "y": {
        "raw": 1246852
      }
    },
    {
      "x": {
        "raw": -131754
      },
      "y": {
        "raw": 1252864
      }
    },
    {
      "x": {
        "raw": -665
      },
      "y": {
        "raw": 1259773
      }
    }
  ],
  "Reorders": [
    [
      0,
      1,
      2,
      3,
      4,
      5,
      6,
      7,
      8,
      9,
      10,
      11,
      12,
      13,
      14,
      15,
      16,
      17,
      18,
      19,
      20,
      21,
      22,
      23,
      24,
      25,
      26,
      27,
      28,
      29,
      30,
      31,
      32,
      33,
      34,
      35,
      36,
      37,
      38,
      39,
      40,
      41,
      42,
      43,
      44,
      45,
      46,
      47,
      48,
      49,
      50,
      51,
      52,
      53,
      54,
      55,
      56,
      57,
      58,
      59,
      60,
      61,
      62,
      63,
      64,
      65,
      66,
      67,
      68,
      69,
      70,
      71,
      72,
      73,
      74,
      75,
      76,
      77,
      78,
      79,
      80,
      81,
      82,
      83,
      84,
      85,
      86,
      87,
      88,
      89,
      90,
      91,
      92,
      93,
      94,
      95,
      96,
      97,
      98,
      99,
      100,
      101,
      102,
      103,
      104,
      105,
      106,
      107,
      108,
      109,
      110,
      111,
      112,
      113,
      114,
      115,
      116,
      117,
      118,
      119,
      120,
      121,
      122,
      123,
      124,
      125,
      126,
      127,
      128,
      129,
      130,
      131,
      132,
      133,
      134,
      135,
      136,
      137,
      138,
      139,
      140,
      141,
      142,
      143,
      144,
      145,
      146,
      147,
      148,
      149,
      150,
      151,
      152,
      153,
      154,
      155,
      156,
      157,
      158,
      159,
      160,
      161,
      162,
      163,
      164,
      165,
      166,
      167,
      168,
      169,
      170,
      171,
      172,
      173,
      174,
      175,
      176,
      177,
      178,
      179,
      180,
      181,
      182,
      183,
      184,
      185,
      186,
      187,
      188,
      189,
      190,
      191,
      192,
      193,
      194,
      195,
      196,
      197,
      198,
      199,
      200,
      201,
      202,
      203,
      204,
      205,
      206,
      207,
      208,
      209,
      210,
      211,
      212,
      213,
      214,
      215,
      216,
      217,
      218,
      219,
      220,
      221,
      222,
      223,
      224,
      225,
      226,
      227,
      228,
      229,
      230,
      231,
      232,
      233,
      234,
      235,
      236,
      237,
      238,
      239,
      240,
      241,
      242,
      243,
      244,
      245,
      246,
      247,
      248,
      249,
      250,
      251,
      252,
      253,
      254,
      255,
      256,
      257,
      258,
      259,
      260,
      261,
      262,
      263,
      264,
      265,
      266,
      267,
      268,
      269,
      270,
      271,
      272,
      273,
      274,
      275,
      276,
      277,
      278,
      279,
      280,
      281,
      282,
      283,
      284,
      285,
      286,
      287,
      288,
      289,
      290,
      291,
      292,
      293,
      294,
      295,
      296,
      297,
      298,
      299,
      300,
      301,
      302,
      303,
      304,
      305,
      306,
      307,
      308,
      309,
      310,
      311,
      312,
      313,
      314,
      315,
      316,
      317,
      318,
      319,
      320,
      321,
      322,
      323,
      324,
      325,
      326,
      327,
      328,
      329,
      330,
      331,
      332,
      333,
      334,
      335,
      336,
      337,
      338,
      339,
      340,
      341,
      342,
      343,
      344,
      345,
      346
    ],
    [
      5,
      10,
      3,
      18,
      1,
      14,
      0,
      12,
      2,
      9,
      33,
      6,
      28,
      7,
      31,
      4,
      16,
      23,
      45,
      19,
      11,
      26,
      17,
      44,
      32,
      13,
      48,
      8,
      63,
      21,
      34,
      65,
      20,
      71,
      39,
      24,
      36,
      30,
      15,
      58,
      29,
      41,
      25,
      50,
      83,
      88,
      22,
      52,
      86,
      35,
      56,
      40,
      74,
      27,
      43,
      42,
      77,
      47,
      80,
      59,
      67,
      61,
      37,
      106,
      64,
      103,
      51,
      70,
      54,
      38,
      93,
      111,
      55,
      57,
      134,
      46,
      60,
      96,
      49,
      82,
      99,
      66,
      76,
      144,
      68,
      85,
      127,
      73,
      133,
      109,
      72,
      75,
      79,
      89,
      62,
      95,
      137,
      81,
      98,
      140,
      53,
      84,
      102,
      124,
      87,
      105,
      152,
      90,
      92,
      130,
      78,
      170,
      112,
      154,
      159,
      118,
      158,
      142,
      115,
      119,
      69,
      104,
      122,
      123,
      183,
      108,
      147,
      186,
      91,
      125,
      175,
      97,
      132,
      192,
      126,
      114,
      136,
      160,
      101,
      143,
      200,
      107,
      121,
      164,
      203,
      110,
      129,
      177,
      94,
      184,
      168,
      117,
      208,
      153,
      193,
      194,
      156,
      100,
      196,
      155,
      139,
      178,
      141,
      146,
      185,
      128,
      226,
      149,
      150,
      131,
      228,
      171,
      210,
      135,
      174,
      213,
      138,
      195,
      217,
      120,
      176,
      199,
      162,
      237,
      163,
      202,
      241,
      165,
      167,
      189,
      151,
      188,
      249,
      231,
      173,
      191,
      234,
      145,
      198,
      215,
      254,
      180,
      219,
      259,
      224,
      201,
      222,
      148,
      258,
      205,
      227,
      169,
      209,
      247,
      211,
      212,
      157,
      161,
      214,
      181,
      220,
      218,
      239,
      197,
      182,
      221,
      279,
      206,
      278,
      187,
      225,
      263,
      190,
      230,
      267,
      232,
      233,
      269,
      235,
      236,
      179,
      287,
      238,
      172,
      244,
      293,
      242,
      282,
      207,
      297,
      246,
      243,
      229,
      250,
      285,
      113,
      253,
      255,
      294,
      301,
      256,
      216,
      257,
      260,
      223,
      262,
      204,
      277,
      265,
      166,
      248,
      268,
      303,
      266,
      252,
      271,
      274,
      275,
      310,
      317,
      240,
      276,
      292,
      273,
      281,
      309,
      284,
      315,
      288,
      286,
      245,
      270,
      289,
      283,
      324,
      291,
      306,
      330,
      116,
      261,
      295,
      333,
      298,
      251,
      290,
      305,
      300,
      264,
      304,
      314,
      336,
      308,
      280,
      311,
      302,
      296,
      316,
      272,
      313,
      327,
      307,
      340,
      299,
      318,
      332,
      320,
      323,
      325,
      328,
      312,
      342,
      326,
      319,
      338,
      331,
      322,
      344,
      334,
      337,
      321,
      346,
      329,
      345,
      335,
      343,
      339,
      341
    ],
    [
      33,
      45,
      18,
      63,
      10,
      71,
      31,
      48,
      5,
      28,
      111,
      14,
      65,
      1,
      88,
      3,
      26,
      44,
      133,
      61,
      12,
      175,
      23,
      83,
      9,
      7,
      86,
      0,
      127,
      41,
      58,
      152,
      6,
      170,
      80,
      21,
      99,
      36,
      2,
      124,
      56,
      103,
      29,
      39,
      144,
      192,
      17,
      77,
      106,
      19,
      96,
      34,
      116,
      4,
      52,
      13,
      119,
      70,
      140,
      16,
      74,
      183,
      30,
      208,
      93,
      166,
      47,
      113,
      50,
      15,
      134,
      228,
      20,
      67,
      137,
      22,
      85,
      178,
      24,
      89,
      161,
      43,
      109,
      203,
      40,
      130,
      226,
      64,
      249,
      172,
      11,
      181,
      82,
      154,
      35,
      102,
      158,
      37,
      105,
      220,
      8,
      57,
      147,
      200,
      60,
      193,
      186,
      32,
      79,
      150,
      46,
      258,
      98,
      213,
      49,
      122,
      196,
      54,
      143,
      217,
      38,
      76,
      126,
      59,
      259,
      95,
      168,
      241,
      55,
      73,
      210,
      51,
      115,
      278,
      231,
      68,
      139,
      234,
      81,
      160,
      254,
      25,
      92,
      164,
      272,
      72,
      112,
      206,
      62,
      132,
      189,
      66,
      279,
      136,
      237,
      84,
      118,
      27,
      251,
      87,
      185,
      269,
      42,
      108,
      202,
      75,
      294,
      129,
      222,
      94,
      310,
      153,
      227,
      78,
      174,
      247,
      101,
      199,
      267,
      53,
      104,
      177,
      182,
      287,
      125,
      239,
      305,
      97,
      149,
      260,
      110,
      171,
      321,
      243,
      117,
      156,
      285,
      91,
      121,
      195,
      301,
      142,
      215,
      317,
      107,
      146,
      236,
      138,
      297,
      167,
      263,
      114,
      188,
      277,
      135,
      191,
      69,
      296,
      131,
      212,
      303,
      159,
      253,
      90,
      123,
      163,
      324,
      256,
      330,
      128,
      205,
      275,
      184,
      209,
      292,
      151,
      225,
      282,
      155,
      233,
      162,
      315,
      180,
      250,
      338,
      311,
      201,
      271,
      148,
      336,
      221,
      289,
      165,
      230,
      309,
      176,
      246,
      173,
      328,
      319,
      265,
      100,
      194,
      268,
      141,
      218,
      145,
      286,
      238,
      306,
      169,
      242,
      318,
      190,
      207,
      262,
      211,
      284,
      340,
      333,
      120,
      214,
      281,
      198,
      235,
      314,
      255,
      327,
      187,
      257,
      204,
      224,
      276,
      264,
      339,
      229,
      298,
      344,
      232,
      157,
      252,
      300,
      274,
      313,
      245,
      326,
      291,
      197,
      283,
      323,
      342,
      248,
      179,
      270,
      288,
      337,
      223,
      302,
      308,
      295,
      244,
      346,
      216,
      273,
      320,
      219,
      290,
      316,
      331,
      261,
      343,
      293,
      304,
      334,
      266,
      240,
      341,
      322,
      332,
      325,
      345,
      280,
      335,
      307,
      329,
      299,
      312
    ],
    [
      88,
      111,
      16,
      133,
      45,
      152,
      71,
      106,
      18,
      127,
      192,
      33,
      86,
      7,
      170,
      10,
      63,
      103,
      208,
      124,
      31,
      144,
      48,
      166,
      65,
      14,
      259,
      5,
      186,
      83,
      99,
      258,
      28,
      249,
      119,
      44,
      161,
      61,
      3,
      185,
      80,
      183,
      12,
      96,
      203,
      228,
      26,
      116,
      226,
      41,
      140,
      58,
      158,
      0,
      77,
      9,
      178,
      93,
      200,
      23,
      113,
      220,
      39,
      278,
      134,
      241,
      56,
      137,
      74,
      1,
      175,
      297,
      6,
      89,
      196,
      21,
      109,
      217,
      36,
      130,
      237,
      52,
      150,
      272,
      70,
      154,
      294,
      85,
      310,
      193,
      11,
      19,
      105,
      213,
      34,
      126,
      234,
      50,
      147,
      254,
      2,
      43,
      168,
      287,
      67,
      189,
      305,
      17,
      102,
      210,
      30,
      321,
      122,
      231,
      47,
      143,
      251,
      64,
      164,
      269,
      4,
      60,
      206,
      13,
      279,
      82,
      172,
      317,
      87,
      118,
      227,
      29,
      139,
      330,
      247,
      57,
      160,
      267,
      73,
      181,
      285,
      32,
      79,
      202,
      301,
      24,
      98,
      222,
      37,
      136,
      243,
      40,
      324,
      156,
      263,
      66,
      177,
      8,
      282,
      76,
      199,
      309,
      22,
      112,
      219,
      20,
      315,
      115,
      239,
      49,
      336,
      153,
      277,
      54,
      174,
      275,
      84,
      195,
      306,
      15,
      108,
      215,
      81,
      328,
      95,
      236,
      319,
      35,
      132,
      256,
      51,
      171,
      340,
      260,
      68,
      191,
      271,
      25,
      92,
      212,
      318,
      121,
      233,
      332,
      75,
      129,
      253,
      110,
      342,
      149,
      268,
      101,
      188,
      286,
      78,
      209,
      38,
      327,
      104,
      230,
      314,
      125,
      250,
      46,
      72,
      163,
      338,
      284,
      344,
      62,
      167,
      300,
      97,
      246,
      326,
      142,
      184,
      311,
      146,
      265,
      27,
      323,
      180,
      281,
      42,
      59,
      176,
      295,
      91,
      346,
      198,
      276,
      114,
      218,
      304,
      117,
      238,
      155,
      339,
      257,
      274,
      69,
      138,
      255,
      55,
      173,
      107,
      288,
      235,
      329,
      131,
      214,
      325,
      94,
      135,
      270,
      151,
      252,
      345,
      337,
      53,
      194,
      290,
      128,
      190,
      205,
      232,
      307,
      148,
      211,
      123,
      169,
      229,
      90,
      316,
      159,
      266,
      343,
      165,
      141,
      207,
      283,
      187,
      308,
      145,
      331,
      201,
      204,
      225,
      242,
      341,
      182,
      100,
      262,
      248,
      273,
      162,
      303,
      302,
      291,
      197,
      335,
      120,
      221,
      320,
      224,
      296,
      245,
      312,
      179,
      334,
      292,
      293,
      313,
      289,
      157,
      322,
      244,
      264,
      298,
      333,
      223,
      299,
      216,
      280,
      240,
      261
    ],
    [
      170,
      192,
      133,
      239,
      111,
      228,
      152,
      186,
      71,
      208,
      249,
      88,
      226,
      127,
      258,
      45,
      144,
      166,
      278,
      183,
      86,
      203,
      106,
      210,
      124,
      63,
      241,
      33,
      279,
      161,
      140,
      294,
      65,
      310,
      200,
      83,
      220,
      103,
      18,
      237,
      119,
      259,
      48,
      158,
      272,
      321,
      28,
      178,
      297,
      80,
      196,
      99,
      217,
      67,
      116,
      31,
      254,
      137,
      269,
      44,
      175,
      287,
      61,
      317,
      193,
      305,
      77,
      213,
      96,
      10,
      234,
      330,
      1,
      134,
      251,
      41,
      154,
      285,
      58,
      172,
      263,
      74,
      243,
      301,
      93,
      256,
      324,
      113,
      336,
      231,
      14,
      26,
      130,
      267,
      39,
      150,
      282,
      56,
      189,
      303,
      5,
      89,
      206,
      315,
      109,
      227,
      328,
      23,
      126,
      247,
      36,
      340,
      147,
      296,
      52,
      168,
      275,
      70,
      185,
      309,
      3,
      199,
      177,
      12,
      319,
      105,
      306,
      333,
      21,
      112,
      260,
      34,
      164,
      342,
      277,
      50,
      181,
      289,
      85,
      202,
      332,
      9,
      102,
      219,
      339,
      19,
      122,
      230,
      40,
      143,
      191,
      47,
      344,
      160,
      284,
      64,
      132,
      0,
      314,
      82,
      146,
      318,
      7,
      92,
      129,
      13,
      327,
      118,
      253,
      30,
      346,
      156,
      271,
      60,
      174,
      313,
      79,
      195,
      326,
      6,
      98,
      215,
      17,
      311,
      115,
      236,
      338,
      29,
      136,
      238,
      43,
      153,
      345,
      184,
      57,
      73,
      300,
      24,
      76,
      125,
      308,
      95,
      218,
      201,
      16,
      87,
      104,
      37,
      337,
      54,
      176,
      11,
      171,
      214,
      49,
      159,
      2,
      222,
      68,
      233,
      273,
      108,
      121,
      4,
      22,
      138,
      334,
      232,
      343,
      55,
      139,
      266,
      51,
      188,
      295,
      84,
      155,
      283,
      81,
      190,
      15,
      323,
      131,
      229,
      20,
      35,
      114,
      262,
      62,
      341,
      212,
      151,
      66,
      205,
      207,
      91,
      194,
      117,
      331,
      325,
      211,
      8,
      135,
      169,
      32,
      149,
      42,
      274,
      148,
      245,
      72,
      198,
      304,
      46,
      101,
      165,
      110,
      264,
      335,
      320,
      38,
      142,
      224,
      25,
      107,
      276,
      180,
      244,
      78,
      187,
      59,
      197,
      235,
      167,
      293,
      128,
      252,
      329,
      145,
      27,
      173,
      261,
      182,
      291,
      94,
      307,
      204,
      97,
      163,
      302,
      322,
      141,
      69,
      162,
      223,
      270,
      75,
      316,
      242,
      257,
      209,
      312,
      53,
      225,
      288,
      268,
      250,
      265,
      298,
      292,
      299,
      246,
      255,
      248,
      123,
      90,
      280,
      221,
      286,
      281,
      290,
      100,
      240,
      120,
      216,
      157,
      179
    ],
    [
      249,
      278,
      228,
      297,
      192,
      310,
      208,
      258,
      170,
      279,
      321,
      152,
      294,
      186,
      305,
      133,
      226,
      241,
      330,
      259,
      61,
      272,
      166,
      287,
      203,
      111,
      301,
      88,
      317,
      220,
      237,
      296,
      127,
      336,
      254,
      144,
      269,
      183,
      71,
      285,
      200,
      303,
      106,
      217,
      324,
      340,
      124,
      234,
      328,
      140,
      251,
      161,
      267,
      63,
      178,
      86,
      282,
      196,
      332,
      103,
      213,
      315,
      119,
      342,
      231,
      333,
      137,
      247,
      158,
      45,
      263,
      344,
      28,
      175,
      236,
      83,
      193,
      309,
      99,
      210,
      319,
      116,
      227,
      284,
      134,
      243,
      339,
      154,
      346,
      277,
      33,
      65,
      172,
      292,
      80,
      189,
      306,
      96,
      206,
      318,
      31,
      113,
      168,
      327,
      150,
      260,
      338,
      48,
      199,
      275,
      44,
      345,
      185,
      289,
      77,
      215,
      302,
      93,
      222,
      314,
      18,
      130,
      239,
      41,
      326,
      147,
      256,
      337,
      58,
      164,
      271,
      17,
      181,
      343,
      286,
      74,
      202,
      300,
      109,
      219,
      313,
      10,
      126,
      250,
      325,
      26,
      143,
      295,
      56,
      160,
      268,
      60,
      334,
      177,
      242,
      89,
      195,
      14,
      298,
      105,
      209,
      311,
      4,
      122,
      225,
      39,
      323,
      139,
      167,
      52,
      341,
      156,
      180,
      70,
      174,
      281,
      85,
      108,
      304,
      5,
      102,
      184,
      23,
      320,
      118,
      142,
      331,
      36,
      136,
      87,
      50,
      153,
      335,
      117,
      67,
      191,
      293,
      12,
      82,
      212,
      308,
      51,
      155,
      173,
      21,
      115,
      198,
      34,
      329,
      101,
      262,
      47,
      171,
      276,
      64,
      97,
      3,
      291,
      98,
      205,
      187,
      49,
      246,
      9,
      19,
      94,
      316,
      148,
      322,
      30,
      149,
      255,
      22,
      131,
      169,
      79,
      128,
      288,
      95,
      201,
      1,
      224,
      112,
      218,
      7,
      13,
      129,
      232,
      43,
      312,
      146,
      252,
      37,
      163,
      204,
      32,
      110,
      92,
      307,
      290,
      194,
      0,
      81,
      214,
      6,
      78,
      29,
      179,
      75,
      270,
      54,
      159,
      266,
      24,
      73,
      176,
      62,
      145,
      299,
      283,
      2,
      46,
      211,
      16,
      55,
      229,
      114,
      245,
      57,
      107,
      25,
      66,
      265,
      40,
      264,
      59,
      162,
      280,
      121,
      11,
      123,
      223,
      233,
      273,
      68,
      244,
      221,
      20,
      132,
      190,
      261,
      104,
      8,
      72,
      135,
      207,
      35,
      248,
      253,
      235,
      76,
      240,
      15,
      125,
      274,
      188,
      138,
      151,
      182,
      84,
      216,
      42,
      141,
      238,
      230,
      27,
      197,
      91,
      90,
      165,
      257,
      38,
      157,
      53,
      120,
      69,
      100
    ],
    [
      310,
      321,
      297,
      330,
      278,
      336,
      294,
      305,
      249,
      317,
      340,
      258,
      324,
      279,
      328,
      228,
      272,
      287,
      342,
      301,
      226,
      303,
      241,
      315,
      259,
      208,
      333,
      192,
      298,
      269,
      285,
      344,
      203,
      346,
      282,
      220,
      296,
      237,
      170,
      309,
      254,
      319,
      186,
      284,
      332,
      345,
      183,
      267,
      339,
      200,
      277,
      217,
      292,
      133,
      234,
      152,
      306,
      251,
      318,
      166,
      247,
      327,
      161,
      337,
      263,
      338,
      196,
      275,
      213,
      111,
      289,
      343,
      127,
      231,
      302,
      144,
      227,
      314,
      140,
      243,
      326,
      178,
      260,
      325,
      89,
      230,
      334,
      193,
      341,
      295,
      106,
      124,
      210,
      246,
      26,
      222,
      316,
      158,
      239,
      313,
      88,
      175,
      256,
      323,
      172,
      271,
      331,
      103,
      189,
      286,
      119,
      335,
      206,
      300,
      137,
      219,
      167,
      154,
      236,
      308,
      71,
      150,
      253,
      86,
      252,
      168,
      268,
      320,
      83,
      185,
      265,
      99,
      202,
      329,
      281,
      116,
      199,
      311,
      134,
      215,
      149,
      63,
      147,
      233,
      128,
      65,
      164,
      101,
      80,
      181,
      262,
      96,
      322,
      177,
      276,
      113,
      73,
      45,
      291,
      130,
      212,
      304,
      48,
      143,
      250,
      61,
      307,
      160,
      180,
      77,
      312,
      195,
      257,
      93,
      174,
      274,
      109,
      191,
      270,
      33,
      126,
      209,
      44,
      290,
      122,
      225,
      293,
      58,
      76,
      242,
      74,
      156,
      299,
      110,
      17,
      171,
      211,
      31,
      105,
      188,
      273,
      102,
      205,
      204,
      28,
      139,
      221,
      41,
      283,
      136,
      238,
      70,
      153,
      91,
      85,
      78,
      18,
      288,
      82,
      49,
      266,
      98,
      138,
      10,
      7,
      115,
      264,
      198,
      280,
      56,
      132,
      169,
      52,
      84,
      187,
      67,
      59,
      248,
      29,
      46,
      3,
      245,
      118,
      75,
      14,
      23,
      112,
      194,
      36,
      261,
      129,
      145,
      50,
      62,
      229,
      64,
      142,
      79,
      244,
      224,
      135,
      5,
      95,
      131,
      12,
      22,
      21,
      72,
      125,
      207,
      47,
      121,
      141,
      34,
      60,
      159,
      57,
      155,
      240,
      223,
      39,
      108,
      232,
      9,
      104,
      190,
      25,
      182,
      43,
      117,
      11,
      40,
      201,
      19,
      197,
      54,
      151,
      216,
      32,
      1,
      184,
      165,
      218,
      148,
      30,
      162,
      55,
      6,
      92,
      214,
      179,
      87,
      0,
      66,
      81,
      173,
      16,
      90,
      235,
      255,
      20,
      157,
      2,
      37,
      123,
      146,
      42,
      97,
      107,
      13,
      120,
      24,
      94,
      176,
      35,
      4,
      100,
      51,
      68,
      163,
      114,
      8,
      69,
      15,
      53,
      27,
      38
    ],
    [
      340,
      342,
      330,
      344,
      321,
      346,
      336,
      328,
      310,
      333,
      345,
      305,
      339,
      317,
      338,
      297,
      324,
      315,
      343,
      257,
      294,
      332,
      29,
      327,
      301,
      278,
      136,
      258,
      337,
      303,
      309,
      169,
      279,
      341,
      319,
      287,
      318,
      285,
      249,
      84,
      282,
      326,
      241,
      296,
      334,
      335,
      259,
      306,
      331,
      272,
      302,
      269,
      314,
      228,
      267,
      226,
      313,
      277,
      325,
      58,
      292,
      323,
      237,
      329,
      289,
      320,
      254,
      286,
      251,
      192,
      300,
      322,
      208,
      263,
      62,
      220,
      260,
      308,
      217,
      275,
      304,
      234,
      271,
      316,
      231,
      284,
      307,
      247,
      312,
      298,
      186,
      203,
      243,
      295,
      200,
      256,
      291,
      196,
      253,
      288,
      170,
      213,
      268,
      290,
      210,
      265,
      293,
      166,
      227,
      262,
      183,
      299,
      239,
      276,
      178,
      236,
      274,
      193,
      233,
      270,
      71,
      189,
      250,
      152,
      273,
      206,
      246,
      283,
      161,
      202,
      311,
      158,
      219,
      280,
      255,
      175,
      215,
      252,
      172,
      230,
      78,
      133,
      168,
      281,
      266,
      144,
      185,
      242,
      140,
      222,
      238,
      137,
      264,
      195,
      235,
      154,
      212,
      111,
      91,
      150,
      209,
      248,
      127,
      164,
      205,
      124,
      90,
      181,
      221,
      119,
      261,
      177,
      218,
      134,
      174,
      232,
      130,
      191,
      229,
      88,
      147,
      225,
      106,
      245,
      143,
      81,
      244,
      103,
      160,
      198,
      116,
      199,
      240,
      214,
      113,
      171,
      211,
      86,
      109,
      188,
      207,
      126,
      35,
      223,
      83,
      139,
      180,
      99,
      216,
      156,
      176,
      96,
      153,
      194,
      93,
      149,
      63,
      107,
      105,
      146,
      204,
      122,
      163,
      1,
      65,
      118,
      197,
      201,
      224,
      80,
      115,
      173,
      77,
      132,
      190,
      89,
      167,
      187,
      85,
      184,
      45,
      182,
      102,
      138,
      48,
      61,
      98,
      155,
      44,
      179,
      112,
      151,
      74,
      108,
      148,
      70,
      125,
      82,
      157,
      162,
      121,
      33,
      79,
      135,
      31,
      95,
      28,
      110,
      92,
      72,
      56,
      87,
      145,
      41,
      67,
      49,
      64,
      117,
      141,
      123,
      18,
      60,
      114,
      26,
      76,
      7,
      22,
      165,
      36,
      142,
      23,
      50,
      101,
      14,
      25,
      47,
      131,
      120,
      129,
      10,
      73,
      13,
      68,
      94,
      52,
      128,
      66,
      39,
      34,
      97,
      100,
      43,
      5,
      40,
      104,
      75,
      12,
      159,
      20,
      59,
      21,
      69,
      3,
      30,
      55,
      57,
      54,
      51,
      42,
      9,
      53,
      19,
      32,
      46,
      17,
      0,
      38,
      16,
      24,
      37,
      27,
      6,
      15,
      2,
      8,
      4,
      11
    ],
    [
      346,
      345,
      344,
      343,
      342,
      341,
      339,
      338,
      336,
      337,
      335,
      340,
      334,
      333,
      331,
      330,
      332,
      327,
      329,
      326,
      328,
      325,
      315,
      323,
      319,
      317,
      320,
      321,
      316,
      318,
      314,
      322,
      324,
      312,
      313,
      303,
      311,
      309,
      310,
      308,
      306,
      304,
      305,
      302,
      32,
      299,
      301,
      300,
      307,
      56,
      298,
      296,
      295,
      297,
      292,
      294,
      291,
      289,
      288,
      287,
      286,
      290,
      285,
      283,
      284,
      293,
      282,
      281,
      277,
      278,
      276,
      280,
      279,
      275,
      274,
      272,
      271,
      270,
      269,
      268,
      273,
      267,
      265,
      266,
      263,
      262,
      264,
      260,
      261,
      257,
      258,
      259,
      256,
      255,
      254,
      253,
      252,
      251,
      250,
      248,
      249,
      247,
      246,
      245,
      243,
      242,
      244,
      241,
      239,
      238,
      237,
      240,
      236,
      235,
      234,
      233,
      232,
      231,
      230,
      229,
      228,
      227,
      225,
      226,
      224,
      222,
      221,
      223,
      220,
      219,
      218,
      217,
      215,
      216,
      214,
      213,
      212,
      211,
      210,
      209,
      207,
      208,
      206,
      205,
      204,
      203,
      202,
      201,
      200,
      199,
      198,
      196,
      197,
      195,
      194,
      193,
      191,
      192,
      190,
      189,
      188,
      187,
      186,
      185,
      184,
      183,
      182,
      181,
      180,
      178,
      179,
      177,
      176,
      175,
      174,
      173,
      172,
      171,
      169,
      170,
      168,
      167,
      166,
      165,
      164,
      163,
      162,
      161,
      160,
      159,
      158,
      156,
      157,
      155,
      154,
      153,
      151,
      152,
      150,
      149,
      148,
      147,
      146,
      145,
      144,
      143,
      142,
      140,
      141,
      139,
      138,
      137,
      136,
      135,
      134,
      132,
      133,
      131,
      130,
      129,
      128,
      126,
      125,
      127,
      124,
      122,
      123,
      121,
      120,
      119,
      118,
      117,
      116,
      115,
      114,
      113,
      112,
      110,
      109,
      108,
      111,
      107,
      105,
      104,
      106,
      103,
      102,
      101,
      99,
      100,
      98,
      97,
      96,
      95,
      94,
      93,
      92,
      89,
      90,
      91,
      87,
      88,
      85,
      84,
      86,
      82,
      83,
      81,
      79,
      78,
      77,
      76,
      75,
      80,
      74,
      73,
      70,
      68,
      69,
      72,
      71,
      67,
      66,
      63,
      64,
      62,
      60,
      59,
      58,
      57,
      28,
      61,
      54,
      65,
      55,
      52,
      51,
      53,
      50,
      45,
      47,
      46,
      43,
      49,
      41,
      42,
      40,
      48,
      39,
      37,
      38,
      36,
      33,
      34,
      30,
      35,
      31,
      25,
      29,
      24,
      44,
      27,
      18,
      23,
      22,
      21,
      19,
      17,
      20,
      10,
      15,
      14,
      6,
      11,
      12,
      26,
      8,
      9,
      7,
      16,
      4,
      5,
      13,
      3,
      2,
      1,
      0
    ],
    [
      12,
      335,
      343,
      329,
      345,
      322,
      341,
      331,
      346,
      316,
      299,
      338,
      307,
      337,
      312,
      344,
      334,
      323,
      280,
      320,
      339,
      304,
      326,
      37,
      325,
      342,
      293,
      340,
      283,
      311,
      308,
      35,
      332,
      261,
      291,
      327,
      288,
      314,
      336,
      290,
      313,
      266,
      328,
      298,
      264,
      240,
      333,
      295,
      244,
      319,
      274,
      318,
      270,
      330,
      300,
      324,
      273,
      284,
      248,
      315,
      281,
      245,
      309,
      216,
      276,
      223,
      306,
      255,
      302,
      321,
      252,
      197,
      317,
      286,
      232,
      303,
      265,
      229,
      296,
      262,
      224,
      292,
      257,
      204,
      289,
      238,
      20,
      271,
      179,
      235,
      31,
      301,
      268,
      211,
      44,
      250,
      207,
      282,
      246,
      187,
      310,
      277,
      242,
      182,
      275,
      218,
      162,
      305,
      253,
      214,
      287,
      157,
      233,
      194,
      285,
      230,
      190,
      263,
      225,
      165,
      297,
      260,
      221,
      294,
      145,
      256,
      198,
      141,
      272,
      236,
      176,
      269,
      212,
      120,
      173,
      267,
      209,
      169,
      243,
      205,
      148,
      278,
      239,
      184,
      123,
      279,
      219,
      180,
      254,
      215,
      155,
      251,
      100,
      195,
      151,
      247,
      188,
      258,
      131,
      227,
      201,
      128,
      259,
      222,
      163,
      241,
      107,
      199,
      159,
      237,
      90,
      177,
      138,
      234,
      174,
      135,
      210,
      171,
      110,
      249,
      206,
      167,
      226,
      91,
      202,
      142,
      53,
      220,
      181,
      121,
      217,
      156,
      69,
      117,
      213,
      191,
      114,
      228,
      231,
      149,
      94,
      189,
      129,
      72,
      203,
      164,
      125,
      200,
      75,
      160,
      16,
      196,
      139,
      97,
      193,
      153,
      208,
      78,
      172,
      132,
      59,
      168,
      104,
      63,
      183,
      185,
      55,
      108,
      38,
      178,
      143,
      84,
      175,
      118,
      81,
      154,
      115,
      62,
      150,
      112,
      192,
      42,
      147,
      146,
      186,
      166,
      126,
      101,
      161,
      27,
      122,
      66,
      158,
      136,
      49,
      137,
      95,
      134,
      25,
      46,
      76,
      170,
      109,
      73,
      152,
      105,
      144,
      68,
      102,
      51,
      48,
      98,
      32,
      140,
      116,
      79,
      113,
      92,
      15,
      9,
      133,
      130,
      87,
      127,
      85,
      54,
      67,
      22,
      119,
      64,
      124,
      96,
      60,
      106,
      11,
      93,
      57,
      8,
      89,
      111,
      70,
      24,
      82,
      40,
      99,
      13,
      47,
      45,
      80,
      30,
      4,
      77,
      88,
      56,
      52,
      29,
      86,
      43,
      50,
      34,
      103,
      2,
      71,
      61,
      6,
      74,
      39,
      23,
      17,
      83,
      0,
      65,
      21,
      19,
      58,
      33,
      7,
      28,
      26,
      36,
      1,
      18,
      3,
      41,
      5,
      10,
      14
    ],
    [
      312,
      299,
      322,
      280,
      329,
      261,
      307,
      293,
      341,
      283,
      240,
      335,
      264,
      316,
      244,
      343,
      26,
      290,
      216,
      30,
      331,
      266,
      320,
      245,
      304,
      44,
      223,
      345,
      38,
      288,
      273,
      197,
      334,
      179,
      40,
      323,
      248,
      308,
      346,
      224,
      291,
      204,
      338,
      270,
      182,
      157,
      337,
      252,
      162,
      325,
      232,
      311,
      229,
      344,
      295,
      339,
      207,
      274,
      187,
      327,
      255,
      165,
      326,
      141,
      235,
      145,
      313,
      214,
      298,
      342,
      211,
      120,
      332,
      276,
      190,
      48,
      257,
      169,
      318,
      238,
      148,
      314,
      218,
      123,
      300,
      194,
      17,
      281,
      100,
      173,
      340,
      333,
      262,
      151,
      319,
      242,
      78,
      302,
      221,
      128,
      336,
      286,
      198,
      107,
      268,
      176,
      90,
      328,
      265,
      155,
      309,
      69,
      246,
      131,
      306,
      225,
      94,
      289,
      201,
      110,
      330,
      271,
      180,
      324,
      91,
      284,
      159,
      72,
      315,
      250,
      138,
      296,
      230,
      53,
      114,
      292,
      205,
      97,
      275,
      184,
      7,
      317,
      256,
      163,
      75,
      301,
      253,
      142,
      303,
      233,
      135,
      282,
      55,
      209,
      117,
      277,
      188,
      321,
      13,
      260,
      167,
      59,
      305,
      236,
      146,
      287,
      42,
      215,
      125,
      285,
      27,
      195,
      121,
      263,
      174,
      101,
      243,
      171,
      62,
      310,
      239,
      149,
      294,
      46,
      219,
      129,
      25,
      269,
      199,
      104,
      267,
      177,
      15,
      84,
      247,
      191,
      81,
      297,
      227,
      153,
      49,
      222,
      132,
      32,
      272,
      202,
      108,
      254,
      11,
      212,
      87,
      251,
      156,
      68,
      231,
      136,
      278,
      51,
      210,
      115,
      35,
      206,
      112,
      279,
      259,
      181,
      20,
      92,
      8,
      237,
      160,
      73,
      234,
      139,
      66,
      213,
      118,
      37,
      189,
      98,
      258,
      22,
      168,
      95,
      152,
      241,
      147,
      76,
      220,
      2,
      143,
      57,
      217,
      122,
      54,
      193,
      102,
      172,
      4,
      24,
      82,
      249,
      150,
      60,
      226,
      130,
      203,
      43,
      126,
      29,
      178,
      105,
      16,
      200,
      175,
      85,
      154,
      64,
      6,
      9,
      228,
      185,
      47,
      208,
      164,
      79,
      109,
      19,
      161,
      89,
      183,
      158,
      70,
      186,
      12,
      137,
      50,
      0,
      134,
      192,
      113,
      34,
      93,
      36,
      127,
      21,
      56,
      166,
      140,
      52,
      1,
      196,
      170,
      96,
      77,
      67,
      144,
      23,
      58,
      74,
      124,
      3,
      133,
      103,
      39,
      99,
      116,
      80,
      14,
      111,
      5,
      106,
      61,
      41,
      86,
      88,
      10,
      83,
      65,
      31,
      28,
      71,
      18,
      119,
      33,
      63,
      45
    ],
    [
      240,
      216,
      280,
      67,
      299,
      179,
      261,
      223,
      312,
      197,
      157,
      293,
      62,
      283,
      162,
      322,
      264,
      244,
      120,
      224,
      307,
      204,
      290,
      182,
      266,
      329,
      141,
      335,
      123,
      245,
      229,
      100,
      316,
      69,
      207,
      273,
      187,
      270,
      341,
      165,
      248,
      145,
      331,
      232,
      22,
      53,
      320,
      211,
      90,
      304,
      190,
      288,
      169,
      343,
      252,
      334,
      148,
      235,
      128,
      323,
      214,
      107,
      308,
      72,
      194,
      91,
      291,
      173,
      274,
      345,
      151,
      38,
      337,
      255,
      131,
      325,
      218,
      110,
      311,
      198,
      65,
      295,
      176,
      75,
      276,
      155,
      55,
      257,
      27,
      135,
      338,
      326,
      238,
      114,
      313,
      201,
      94,
      298,
      180,
      78,
      346,
      281,
      159,
      59,
      262,
      138,
      42,
      327,
      242,
      117,
      314,
      25,
      221,
      97,
      300,
      184,
      81,
      284,
      163,
      13,
      344,
      265,
      142,
      339,
      46,
      246,
      121,
      20,
      318,
      225,
      101,
      302,
      205,
      15,
      84,
      286,
      188,
      66,
      268,
      167,
      49,
      342,
      250,
      125,
      32,
      332,
      230,
      104,
      319,
      209,
      108,
      306,
      8,
      191,
      68,
      289,
      171,
      340,
      51,
      271,
      146,
      35,
      333,
      253,
      129,
      203,
      11,
      233,
      87,
      309,
      4,
      212,
      92,
      292,
      174,
      73,
      275,
      153,
      37,
      336,
      256,
      132,
      328,
      9,
      236,
      112,
      6,
      315,
      215,
      76,
      296,
      195,
      2,
      57,
      277,
      156,
      54,
      330,
      260,
      136,
      40,
      239,
      115,
      24,
      324,
      219,
      95,
      303,
      16,
      199,
      79,
      282,
      177,
      43,
      263,
      139,
      317,
      29,
      243,
      118,
      17,
      222,
      98,
      241,
      301,
      202,
      7,
      82,
      0,
      285,
      181,
      60,
      267,
      160,
      47,
      247,
      122,
      30,
      227,
      149,
      321,
      19,
      206,
      102,
      305,
      287,
      185,
      64,
      269,
      1,
      164,
      50,
      251,
      143,
      34,
      231,
      126,
      210,
      63,
      18,
      105,
      310,
      189,
      85,
      294,
      172,
      272,
      52,
      147,
      36,
      234,
      130,
      21,
      254,
      213,
      109,
      193,
      89,
      3,
      12,
      297,
      168,
      70,
      279,
      154,
      39,
      134,
      23,
      166,
      113,
      186,
      217,
      93,
      152,
      14,
      196,
      74,
      5,
      175,
      278,
      137,
      56,
      116,
      41,
      220,
      26,
      96,
      258,
      200,
      77,
      31,
      178,
      249,
      140,
      119,
      58,
      226,
      28,
      99,
      80,
      259,
      10,
      228,
      183,
      44,
      127,
      124,
      103,
      48,
      208,
      61,
      170,
      83,
      150,
      237,
      192,
      33,
      144,
      158,
      86,
      45,
      161,
      71,
      133,
      88,
      111,
      106
    ],
    [
      157,
      40,
      179,
      120,
      216,
      100,
      197,
      162,
      261,
      141,
      69,
      240,
      123,
      223,
      90,
      280,
      182,
      50,
      53,
      145,
      244,
      24,
      224,
      107,
      204,
      283,
      72,
      299,
      25,
      187,
      165,
      38,
      264,
      27,
      128,
      245,
      110,
      229,
      312,
      91,
      207,
      55,
      293,
      169,
      20,
      15,
      266,
      148,
      42,
      248,
      131,
      232,
      114,
      322,
      211,
      307,
      75,
      190,
      59,
      290,
      173,
      46,
      273,
      21,
      151,
      32,
      252,
      94,
      214,
      329,
      97,
      8,
      316,
      194,
      78,
      304,
      176,
      62,
      288,
      155,
      49,
      270,
      138,
      35,
      235,
      117,
      11,
      218,
      0,
      101,
      335,
      320,
      198,
      81,
      291,
      180,
      66,
      274,
      135,
      51,
      341,
      255,
      142,
      22,
      238,
      121,
      13,
      331,
      221,
      84,
      308,
      4,
      201,
      68,
      295,
      159,
      77,
      276,
      163,
      37,
      343,
      257,
      125,
      334,
      16,
      242,
      104,
      3,
      323,
      205,
      87,
      311,
      184,
      2,
      54,
      281,
      167,
      57,
      262,
      146,
      29,
      337,
      246,
      108,
      17,
      325,
      225,
      92,
      313,
      188,
      73,
      298,
      6,
      171,
      76,
      284,
      149,
      345,
      43,
      265,
      129,
      30,
      338,
      230,
      112,
      326,
      7,
      209,
      95,
      314,
      9,
      191,
      60,
      300,
      174,
      47,
      268,
      153,
      36,
      346,
      250,
      132,
      327,
      19,
      233,
      115,
      12,
      318,
      212,
      98,
      302,
      195,
      1,
      79,
      286,
      156,
      61,
      339,
      271,
      136,
      34,
      253,
      118,
      28,
      332,
      236,
      102,
      319,
      31,
      215,
      82,
      306,
      177,
      64,
      289,
      160,
      344,
      65,
      256,
      139,
      23,
      239,
      122,
      342,
      237,
      219,
      39,
      85,
      5,
      309,
      199,
      67,
      292,
      181,
      52,
      275,
      164,
      44,
      260,
      143,
      340,
      14,
      243,
      105,
      333,
      315,
      222,
      89,
      296,
      63,
      185,
      70,
      277,
      168,
      56,
      263,
      126,
      247,
      10,
      26,
      130,
      336,
      227,
      109,
      328,
      210,
      324,
      74,
      189,
      58,
      282,
      140,
      41,
      303,
      267,
      150,
      231,
      147,
      18,
      183,
      330,
      202,
      93,
      317,
      193,
      113,
      172,
      96,
      269,
      154,
      226,
      251,
      134,
      258,
      48,
      234,
      116,
      88,
      213,
      321,
      206,
      80,
      175,
      99,
      287,
      83,
      158,
      305,
      254,
      119,
      33,
      203,
      310,
      217,
      196,
      137,
      294,
      103,
      161,
      152,
      301,
      45,
      297,
      285,
      86,
      220,
      200,
      178,
      124,
      279,
      71,
      249,
      144,
      127,
      241,
      278,
      106,
      208,
      186,
      166,
      111,
      259,
      133,
      228,
      170,
      272,
      192
    ],
    [
      27,
      69,
      120,
      53,
      100,
      38,
      90,
      142,
      179,
      72,
      14,
      157,
      55,
      141,
      25,
      197,
      123,
      107,
      15,
      91,
      162,
      75,
      145,
      42,
      128,
      229,
      6,
      240,
      8,
      110,
      94,
      11,
      182,
      4,
      59,
      165,
      46,
      148,
      261,
      32,
      131,
      20,
      244,
      114,
      22,
      2,
      224,
      78,
      13,
      187,
      62,
      169,
      49,
      280,
      151,
      264,
      35,
      135,
      37,
      245,
      97,
      24,
      204,
      89,
      81,
      16,
      190,
      66,
      173,
      299,
      51,
      0,
      283,
      155,
      54,
      216,
      117,
      40,
      248,
      101,
      29,
      207,
      84,
      17,
      194,
      68,
      7,
      176,
      5,
      73,
      293,
      266,
      159,
      57,
      252,
      121,
      43,
      232,
      104,
      30,
      312,
      211,
      87,
      21,
      214,
      92,
      9,
      290,
      198,
      76,
      273,
      1,
      180,
      60,
      138,
      125,
      47,
      235,
      108,
      34,
      322,
      218,
      112,
      307,
      19,
      201,
      95,
      12,
      223,
      163,
      79,
      270,
      167,
      3,
      64,
      255,
      146,
      36,
      238,
      129,
      23,
      329,
      221,
      115,
      26,
      316,
      205,
      98,
      288,
      188,
      82,
      274,
      31,
      171,
      50,
      257,
      149,
      335,
      52,
      242,
      132,
      39,
      320,
      225,
      118,
      304,
      48,
      184,
      102,
      291,
      10,
      191,
      85,
      276,
      174,
      67,
      262,
      153,
      56,
      341,
      246,
      136,
      331,
      41,
      230,
      122,
      28,
      313,
      212,
      74,
      295,
      195,
      18,
      70,
      281,
      314,
      58,
      334,
      265,
      156,
      61,
      250,
      139,
      44,
      323,
      233,
      105,
      311,
      45,
      215,
      109,
      298,
      206,
      93,
      284,
      177,
      343,
      77,
      268,
      160,
      83,
      253,
      126,
      337,
      326,
      236,
      130,
      116,
      154,
      306,
      309,
      158,
      300,
      199,
      99,
      286,
      181,
      96,
      271,
      164,
      345,
      86,
      296,
      143,
      338,
      327,
      251,
      119,
      315,
      33,
      219,
      113,
      302,
      202,
      80,
      267,
      185,
      275,
      63,
      65,
      137,
      346,
      301,
      147,
      339,
      175,
      256,
      134,
      196,
      124,
      209,
      178,
      144,
      319,
      217,
      189,
      277,
      168,
      111,
      127,
      344,
      260,
      150,
      332,
      222,
      161,
      200,
      103,
      239,
      210,
      305,
      272,
      193,
      333,
      166,
      282,
      172,
      71,
      263,
      342,
      220,
      140,
      247,
      186,
      303,
      106,
      213,
      328,
      310,
      227,
      88,
      259,
      340,
      241,
      289,
      208,
      324,
      152,
      243,
      234,
      308,
      133,
      336,
      287,
      231,
      279,
      269,
      325,
      183,
      330,
      228,
      317,
      226,
      203,
      294,
      321,
      170,
      237,
      285,
      254,
      192,
      318,
      292,
      297,
      249,
      278,
      258
    ],
    [
      27,
      15,
      53,
      8,
      69,
      4,
      38,
      25,
      100,
      20,
      1,
      90,
      13,
      72,
      11,
      120,
      42,
      32,
      2,
      46,
      55,
      35,
      91,
      22,
      75,
      141,
      16,
      157,
      7,
      59,
      62,
      6,
      107,
      0,
      49,
      110,
      24,
      94,
      179,
      37,
      78,
      29,
      162,
      81,
      17,
      3,
      145,
      66,
      9,
      128,
      51,
      131,
      54,
      197,
      97,
      123,
      40,
      68,
      19,
      165,
      84,
      21,
      148,
      12,
      43,
      28,
      114,
      30,
      135,
      216,
      57,
      5,
      182,
      101,
      34,
      204,
      104,
      36,
      169,
      87,
      124,
      151,
      73,
      23,
      155,
      60,
      14,
      138,
      10,
      47,
      223,
      224,
      121,
      50,
      207,
      125,
      39,
      190,
      108,
      41,
      261,
      173,
      76,
      26,
      117,
      79,
      48,
      244,
      142,
      64,
      187,
      18,
      92,
      67,
      211,
      129,
      52,
      194,
      112,
      61,
      280,
      159,
      85,
      264,
      44,
      180,
      82,
      127,
      245,
      146,
      74,
      229,
      149,
      33,
      70,
      214,
      95,
      56,
      198,
      115,
      58,
      240,
      201,
      98,
      65,
      266,
      184,
      102,
      248,
      167,
      89,
      232,
      31,
      132,
      137,
      176,
      136,
      299,
      77,
      205,
      118,
      80,
      293,
      188,
      122,
      273,
      338,
      246,
      105,
      270,
      71,
      156,
      109,
      218,
      174,
      93,
      221,
      139,
      99,
      312,
      163,
      160,
      283,
      83,
      195,
      126,
      111,
      252,
      171,
      130,
      274,
      153,
      45,
      113,
      235,
      177,
      96,
      307,
      242,
      143,
      147,
      225,
      164,
      103,
      290,
      209,
      150,
      288,
      63,
      236,
      134,
      276,
      199,
      116,
      238,
      181,
      322,
      119,
      262,
      185,
      144,
      230,
      168,
      316,
      304,
      233,
      86,
      154,
      106,
      291,
      215,
      158,
      255,
      202,
      227,
      265,
      193,
      186,
      268,
      175,
      335,
      241,
      253,
      189,
      329,
      323,
      219,
      172,
      308,
      88,
      222,
      339,
      298,
      206,
      140,
      284,
      196,
      271,
      305,
      166,
      210,
      341,
      256,
      200,
      331,
      239,
      325,
      178,
      243,
      161,
      281,
      213,
      183,
      313,
      212,
      231,
      275,
      259,
      133,
      152,
      343,
      277,
      317,
      334,
      260,
      310,
      251,
      237,
      289,
      247,
      191,
      306,
      234,
      326,
      220,
      292,
      217,
      170,
      282,
      345,
      285,
      203,
      269,
      279,
      319,
      208,
      267,
      257,
      263,
      254,
      192,
      296,
      346,
      340,
      250,
      294,
      332,
      286,
      309,
      272,
      300,
      228,
      337,
      318,
      226,
      315,
      303,
      295,
      311,
      344,
      258,
      333,
      302,
      287,
      328,
      342,
      249,
      324,
      320,
      314,
      301,
      336,
      278,
      330,
      297,
      327,
      321
    ],
    [
      4,
      2,
      8,
      0,
      15,
      1,
      11,
      13,
      27,
      6,
      3,
      25,
      7,
      20,
      9,
      38,
      16,
      22,
      5,
      19,
      42,
      48,
      32,
      17,
      35,
      55,
      14,
      53,
      12,
      24,
      37,
      31,
      46,
      10,
      29,
      59,
      30,
      62,
      69,
      23,
      51,
      21,
      72,
      40,
      26,
      18,
      91,
      43,
      28,
      78,
      34,
      49,
      39,
      100,
      54,
      90,
      36,
      68,
      41,
      66,
      57,
      58,
      94,
      203,
      47,
      65,
      81,
      50,
      84,
      120,
      52,
      33,
      123,
      60,
      77,
      128,
      73,
      56,
      110,
      76,
      61,
      114,
      64,
      44,
      101,
      67,
      63,
      87,
      45,
      74,
      141,
      145,
      92,
      70,
      148,
      95,
      93,
      97,
      79,
      80,
      157,
      121,
      82,
      83,
      104,
      85,
      86,
      75,
      125,
      89,
      131,
      71,
      112,
      113,
      151,
      98,
      96,
      135,
      102,
      99,
      179,
      108,
      122,
      182,
      124,
      129,
      126,
      106,
      165,
      115,
      105,
      169,
      132,
      88,
      109,
      173,
      118,
      116,
      176,
      139,
      140,
      197,
      142,
      143,
      103,
      204,
      149,
      147,
      187,
      136,
      130,
      190,
      127,
      153,
      134,
      117,
      156,
      216,
      137,
      163,
      164,
      119,
      223,
      146,
      185,
      224,
      166,
      188,
      150,
      211,
      111,
      171,
      172,
      214,
      174,
      154,
      155,
      160,
      158,
      240,
      201,
      181,
      245,
      161,
      205,
      168,
      152,
      207,
      191,
      247,
      232,
      195,
      133,
      175,
      235,
      177,
      178,
      244,
      159,
      199,
      183,
      180,
      219,
      144,
      266,
      225,
      189,
      229,
      338,
      212,
      167,
      194,
      209,
      193,
      218,
      236,
      261,
      196,
      221,
      202,
      217,
      184,
      215,
      264,
      162,
      230,
      186,
      206,
      170,
      252,
      233,
      210,
      255,
      138,
      213,
      257,
      239,
      220,
      262,
      222,
      280,
      226,
      246,
      227,
      283,
      290,
      250,
      251,
      288,
      192,
      253,
      254,
      242,
      256,
      200,
      276,
      275,
      268,
      208,
      238,
      243,
      299,
      265,
      231,
      293,
      281,
      248,
      234,
      271,
      237,
      291,
      260,
      241,
      274,
      298,
      263,
      284,
      267,
      228,
      259,
      312,
      286,
      289,
      307,
      302,
      269,
      198,
      272,
      273,
      277,
      308,
      295,
      282,
      320,
      258,
      300,
      285,
      249,
      313,
      322,
      107,
      324,
      292,
      301,
      311,
      279,
      296,
      331,
      304,
      306,
      278,
      314,
      329,
      318,
      309,
      287,
      334,
      315,
      270,
      303,
      323,
      297,
      335,
      327,
      294,
      326,
      319,
      325,
      305,
      341,
      310,
      337,
      332,
      317,
      339,
      345,
      321,
      316,
      333,
      328,
      330,
      346,
      336,
      344,
      343,
      342,
      340
    ]
  ]
}